shuhari_toolkit/__init__.py
shuhari_toolkit/collections.py
shuhari_toolkit/fileutils.py
shuhari_toolkit/hashing.py
shuhari_toolkit-0.0.3.dist-info/LICENSE
shuhari_toolkit-0.0.3.dist-info/METADATA
shuhari_toolkit-0.0.3.dist-info/WHEEL
shuhari_toolkit-0.0.3.dist-info/top_level.txt
shuhari_toolkit-0.0.3.dist-info/RECORD
