Metadata-Version: 2.1
Name: shuhari-toolkit
Version: 0.0.3
Summary: UNKNOWN
Home-page: https://github.com/shuhari/shuhari-toolkit
Author: shuhari
Author-email: shuhari@outlook.com
License: UNKNOWN
Platform: UNKNOWN
Classifier: Programming Language :: Python :: 3
Classifier: License :: OSI Approved :: MIT License
Classifier: Operating System :: OS Independent
Requires-Python: >=3.7
